dragodis/__init__.py
dragodis/api.py
dragodis/constants.py
dragodis/exceptions.py
dragodis/utils.py
dragodis/ghidra/__init__.py
dragodis/ghidra/data_type.py
dragodis/ghidra/disassembler.py
dragodis/ghidra/flat.py
dragodis/ghidra/flowchart.py
dragodis/ghidra/function.py
dragodis/ghidra/function_argument_location.py
dragodis/ghidra/function_signature.py
dragodis/ghidra/instruction.py
dragodis/ghidra/line.py
dragodis/ghidra/memory.py
dragodis/ghidra/operand.py
dragodis/ghidra/operand_value.py
dragodis/ghidra/reference.py
dragodis/ghidra/segment.py
dragodis/ghidra/stack.py
dragodis/ghidra/string.py
dragodis/ghidra/symbol.py
dragodis/ghidra/utils.py
dragodis/ghidra/variable.py
dragodis/ida/__init__.py
dragodis/ida/constants.py
dragodis/ida/data_type.py
dragodis/ida/disassembler.py
dragodis/ida/flat.py
dragodis/ida/flowchart.py
dragodis/ida/function.py
dragodis/ida/function_argument_location.py
dragodis/ida/function_signature.py
dragodis/ida/ida_server.py
dragodis/ida/instruction.py
dragodis/ida/line.py
dragodis/ida/memory.py
dragodis/ida/operand.py
dragodis/ida/operand_value.py
dragodis/ida/reference.py
dragodis/ida/segment.py
dragodis/ida/stack.py
dragodis/ida/string.py
dragodis/ida/symbol.py
dragodis/ida/variable.py
dragodis/ida/sdk/__init__.py
dragodis/ida/sdk/ida_arm.py
dragodis/ida/sdk/ida_helpers.py
dragodis/ida/sdk/ida_intel.py
dragodis/interface/__init__.py
dragodis/interface/data_type.py
dragodis/interface/disassembler.py
dragodis/interface/flat.py
dragodis/interface/flowchart.py
dragodis/interface/function.py
dragodis/interface/function_argument_location.py
dragodis/interface/function_signature.py
dragodis/interface/instruction.py
dragodis/interface/line.py
dragodis/interface/memory.py
dragodis/interface/operand.py
dragodis/interface/operand_value.py
dragodis/interface/reference.py
dragodis/interface/segment.py
dragodis/interface/stack.py
dragodis/interface/string.py
dragodis/interface/structure.py
dragodis/interface/symbol.py
dragodis/interface/types.py
dragodis-1.0.0.dist-info/LICENSE.txt
dragodis-1.0.0.dist-info/METADATA
dragodis-1.0.0.dist-info/WHEEL
dragodis-1.0.0.dist-info/top_level.txt
dragodis-1.0.0.dist-info/RECORD
