Metadata-Version: 2.1
Name: dragodis
Version: 1.0.0
Summary: A universal interface for running scripts under multiple disassemblers.
Home-page: https://github.com/dod-cyber-crime-center/dragodis
Author: DC3
License: MIT
Keywords: malware,ida,idapro,ghidra,disassembler
Classifier: Development Status :: 4 - Beta
Classifier: Intended Audience :: Developers
Classifier: License :: OSI Approved :: MIT License
Classifier: Programming Language :: Python :: 3
Classifier: Programming Language :: Python :: 3.9
Classifier: Programming Language :: Python :: 3.10
Classifier: Programming Language :: Python :: 3.11
Classifier: Programming Language :: Python :: 3.12
Requires-Python: >=3.9
License-File: LICENSE.txt
Requires-Dist: bytesparse
Requires-Dist: capstone
Requires-Dist: rpyc
Requires-Dist: pyhidra >=0.4.0
Requires-Dist: pefile
Requires-Dist: pyelftools
Requires-Dist: pywin32 ; platform_system == "Windows"
Provides-Extra: testing
Requires-Dist: pytest >=3.0.0 ; extra == 'testing'
Requires-Dist: pytest-datadir ; extra == 'testing'
